
[
    {
        "image_url": "https://i.ibb.co/Dg1zKbk/226.jpg",
        "id": "0",
        "name": "All book"
        
    },
    {
        "image_url": "https://i.ibb.co/0nBxft5/1157.jpg",
        "id": "1",
        "name": "Moby-Dick"
    },
    {
        "image_url": "https://i.ibb.co/vkMwN4n/7492664.jpg",
        "id": "2",
        "name": " the Lighthouse"
    },
    {
        "image_url": "https://i.ibb.co/WKwBbT8/19021605.jpg",
        "id": "3",
        "name": "the Lighthouse"
    },
    {
        "image_url": "https://i.ibb.co/ngSbB94/english-books-blue-background.jpg",
        "id": "4",
        "name": "Sports"
    },
    {
        "image_url": "https://i.ibb.co/SKG52k7/literature-love-concept.jpg",
        "id": "5",
        "name": "Entertainment"
    },
    {
        "image_url": "https://i.ibb.co/fv2wLwj/OJK9410.jpg",
        "id": "6",
        "name": "Culture"
    },
    {
        "image_url": "https://i.ibb.co/TvpnkYz/ORJ9YV0.jpg",
        "id": "7",
        "name": "Catcher in the Rye"
    },
    {
        "image_url": "https://i.ibb.co/sqZ3LnY/ORJA090.jpg",
        "id": "8",
        "name": "Harper Lee"
    },
    {
        "image_url": "https://i.ibb.co/qnF5kFG/english-language-books-arrangement.jpg",
        "id": "9",
        "name": "1984"
    },
    {
        "image_url": "https://i.ibb.co/dJDvsfQ/flat-lay-school-essentials-with-books-clock.jpg",
        "id": "10",
        "name": "To Kill a Mockingbird"
    },
    {
        "image_url": "https://i.ibb.co/s31rqGb/pngwing-1-removebg-preview.png",
        "id": "11",
        "name": "The Odyssey"
    },
    {
        "image_url": "https://i.ibb.co/9pt0Z2F/english-books-blue-background-high-angle.jpg",
        "id": "12",
        "name": "The Hobbit"
    },
    {
        "image_url": "https://i.ibb.co/w7tDZrq/4824032.jpg",
        "id": "13",
        "name": "Frankenstein"
    },
    {
        "image_url": "https://i.ibb.co/T86DKNK/three-books-near-bookshelf.jpg",
        "id": "14",
        "name": "Brave New World"
    }
  
    
]
